{"text": " So here's my Frieden STW-10 and today I wanted to respond to one of the most frequent comments I get which is try to divide by zero is awesome and dangerous if divide by zero does it catch fire try to divide by zero please make a division by zero and then I ask a guy to try it by himself and say I only do it on my piano which actually wouldn't help again I was kind of reluctant to do it and I had to think for a while what would happen if I did it and I convinced myself that no it wouldn't catch fire so it would be a very popular YouTube video so let's try it let's divide by zero and see what happens so let me clear everything and enter 355 as the dividend okay so we have a 355 out there there you go 355 right here and now we are going to divide by zero so I'll do a keyboard clear plump there's nothing on the keyboard and I'll hit the two buttons and we'll see what happens before that I will reset it other direction reset it here because it's more spectacular and okay off we go so it's a freedom you need to press two buttons to divide the right one and the left one and what happens that it gets into an infinite loop and will never stop and I guess it heats up so eventually it would catch fire but guess what they thought about it there's a button here it's called div stop and I guess that was made especially for idiots making YouTube videos and they had lots of foresight so this is what it does it just gets set in an infinite infinite loop but let's understand why that is so let's clear everything and I'll do a regular division though of my favorite one which gives pi 355 dividend divided by 113 and again I'll try to do it from the edge here so what happens is that in order to do divisions what it actually does is successive subtractions and does it as we do it in school is trial and error so it will try to subtract what I just entered which is 113 from this number and trying progressively know this time 10, 900, 1000 until it hits over here and finally it subtracts enough of a chunk that it overflows and it tells it it has subtracted too much and then it starts to move it one to the left and subtract smaller amounts and that's how it does the division eventually so let's see how that works see it move move move move move move move ding it overflows and eventually it divide in and it's in the 3.141592 something it's the approximation of pi so what happens that when you divide by zero is just subtract nothing and so it can never overflow and it gets stuck in an infinite loop so here you go here you have it divide by zero on a Frieden STW10 let's do it again as clear enter some kind of stupid number dividend all to the right here the keyboard divide by zero and watch the smoke okay we'll do that forever good night a brilliant cast Jack Lemon in a delightful role which gives full reign to Jack's amazing versatility you", "segments": [{"id": 0, "seek": 0, "start": 0.0, "end": 10.4, "text": " So here's my Frieden STW-10 and today I wanted to respond to one of the most", "tokens": [50364, 407, 510, 311, 452, 17605, 268, 4904, 54, 12, 3279, 293, 965, 286, 1415, 281, 4196, 281, 472, 295, 264, 881, 50884], "temperature": 0.0, "avg_logprob": -0.19848052263259888, "compression_ratio": 1.6031746031746033, "no_speech_prob": 0.2806999385356903}, {"id": 1, "seek": 0, "start": 10.4, "end": 17.76, "text": " frequent comments I get which is try to divide by zero is awesome and", "tokens": [50884, 18004, 3053, 286, 483, 597, 307, 853, 281, 9845, 538, 4018, 307, 3476, 293, 51252], "temperature": 0.0, "avg_logprob": -0.19848052263259888, "compression_ratio": 1.6031746031746033, "no_speech_prob": 0.2806999385356903}, {"id": 2, "seek": 0, "start": 17.76, "end": 24.16, "text": " dangerous if divide by zero does it catch fire try to divide by zero please", "tokens": [51252, 5795, 498, 9845, 538, 4018, 775, 309, 3745, 2610, 853, 281, 9845, 538, 4018, 1767, 51572], "temperature": 0.0, "avg_logprob": -0.19848052263259888, "compression_ratio": 1.6031746031746033, "no_speech_prob": 0.2806999385356903}, {"id": 3, "seek": 0, "start": 24.16, "end": 28.68, "text": " make a division by zero and then I ask a guy to try it by himself and say I only", "tokens": [51572, 652, 257, 10044, 538, 4018, 293, 550, 286, 1029, 257, 2146, 281, 853, 309, 538, 3647, 293, 584, 286, 787, 51798], "temperature": 0.0, "avg_logprob": -0.19848052263259888, "compression_ratio": 1.6031746031746033, "no_speech_prob": 0.2806999385356903}, {"id": 4, "seek": 2868, "start": 28.68, "end": 34.04, "text": " do it on my piano which actually wouldn't help again I was kind of reluctant", "tokens": [50364, 360, 309, 322, 452, 9211, 597, 767, 2759, 380, 854, 797, 286, 390, 733, 295, 33677, 50632], "temperature": 0.0, "avg_logprob": -0.1789263440417005, "compression_ratio": 1.5891891891891892, "no_speech_prob": 0.06033078953623772}, {"id": 5, "seek": 2868, "start": 34.04, "end": 37.84, "text": " to do it and I had to think for a while what would happen if I did it and I", "tokens": [50632, 281, 360, 309, 293, 286, 632, 281, 519, 337, 257, 1339, 437, 576, 1051, 498, 286, 630, 309, 293, 286, 50822], "temperature": 0.0, "avg_logprob": -0.1789263440417005, "compression_ratio": 1.5891891891891892, "no_speech_prob": 0.06033078953623772}, {"id": 6, "seek": 2868, "start": 37.84, "end": 43.6, "text": " convinced myself that no it wouldn't catch fire so it would be a very", "tokens": [50822, 12561, 2059, 300, 572, 309, 2759, 380, 3745, 2610, 370, 309, 576, 312, 257, 588, 51110], "temperature": 0.0, "avg_logprob": -0.1789263440417005, "compression_ratio": 1.5891891891891892, "no_speech_prob": 0.06033078953623772}, {"id": 7, "seek": 2868, "start": 43.6, "end": 49.96, "text": " popular YouTube video so let's try it let's divide by zero and see what", "tokens": [51110, 3743, 3088, 960, 370, 718, 311, 853, 309, 718, 311, 9845, 538, 4018, 293, 536, 437, 51428], "temperature": 0.0, "avg_logprob": -0.1789263440417005, "compression_ratio": 1.5891891891891892, "no_speech_prob": 0.06033078953623772}, {"id": 8, "seek": 4996, "start": 49.96, "end": 63.32, "text": " happens so let me clear everything and enter 355 as the dividend okay so we have", "tokens": [50364, 2314, 370, 718, 385, 1850, 1203, 293, 3242, 6976, 20, 382, 264, 29796, 1392, 370, 321, 362, 51032], "temperature": 0.0, "avg_logprob": -0.25086866423141124, "compression_ratio": 1.4495412844036697, "no_speech_prob": 0.08867625892162323}, {"id": 9, "seek": 4996, "start": 63.32, "end": 75.36, "text": " a 355 out there there you go 355 right here and now we are going to divide by", "tokens": [51032, 257, 6976, 20, 484, 456, 456, 291, 352, 6976, 20, 558, 510, 293, 586, 321, 366, 516, 281, 9845, 538, 51634], "temperature": 0.0, "avg_logprob": -0.25086866423141124, "compression_ratio": 1.4495412844036697, "no_speech_prob": 0.08867625892162323}, {"id": 10, "seek": 7536, "start": 75.36, "end": 81.48, "text": " zero so I'll do a keyboard clear plump there's nothing on the keyboard and I'll", "tokens": [50364, 4018, 370, 286, 603, 360, 257, 10186, 1850, 499, 1420, 456, 311, 1825, 322, 264, 10186, 293, 286, 603, 50670], "temperature": 0.0, "avg_logprob": -0.2000856766333947, "compression_ratio": 1.6737967914438503, "no_speech_prob": 0.13632908463478088}, {"id": 11, "seek": 7536, "start": 81.48, "end": 87.08, "text": " hit the two buttons and we'll see what happens before that I will reset it", "tokens": [50670, 2045, 264, 732, 9905, 293, 321, 603, 536, 437, 2314, 949, 300, 286, 486, 14322, 309, 50950], "temperature": 0.0, "avg_logprob": -0.2000856766333947, "compression_ratio": 1.6737967914438503, "no_speech_prob": 0.13632908463478088}, {"id": 12, "seek": 7536, "start": 87.08, "end": 95.4, "text": " other direction reset it here because it's more spectacular and okay off we go", "tokens": [50950, 661, 3513, 14322, 309, 510, 570, 309, 311, 544, 18149, 293, 1392, 766, 321, 352, 51366], "temperature": 0.0, "avg_logprob": -0.2000856766333947, "compression_ratio": 1.6737967914438503, "no_speech_prob": 0.13632908463478088}, {"id": 13, "seek": 7536, "start": 95.4, "end": 99.24, "text": " so it's a freedom you need to press two buttons to divide the right one and the", "tokens": [51366, 370, 309, 311, 257, 5645, 291, 643, 281, 1886, 732, 9905, 281, 9845, 264, 558, 472, 293, 264, 51558], "temperature": 0.0, "avg_logprob": -0.2000856766333947, "compression_ratio": 1.6737967914438503, "no_speech_prob": 0.13632908463478088}, {"id": 14, "seek": 9924, "start": 99.24, "end": 101.52, "text": " left one", "tokens": [50364, 1411, 472, 50478], "temperature": 0.0, "avg_logprob": -0.26365417730612833, "compression_ratio": 1.6266666666666667, "no_speech_prob": 0.05744779855012894}, {"id": 15, "seek": 9924, "start": 104.6, "end": 111.83999999999999, "text": " and what happens that it gets into an infinite loop and will never stop and I", "tokens": [50632, 293, 437, 2314, 300, 309, 2170, 666, 364, 13785, 6367, 293, 486, 1128, 1590, 293, 286, 50994], "temperature": 0.0, "avg_logprob": -0.26365417730612833, "compression_ratio": 1.6266666666666667, "no_speech_prob": 0.05744779855012894}, {"id": 16, "seek": 9924, "start": 111.83999999999999, "end": 116.96, "text": " guess it heats up so eventually it would catch fire but guess what they thought", "tokens": [50994, 2041, 309, 41035, 493, 370, 4728, 309, 576, 3745, 2610, 457, 2041, 437, 436, 1194, 51250], "temperature": 0.0, "avg_logprob": -0.26365417730612833, "compression_ratio": 1.6266666666666667, "no_speech_prob": 0.05744779855012894}, {"id": 17, "seek": 9924, "start": 116.96, "end": 123.75999999999999, "text": " about it there's a button here it's called div stop and I guess that was made", "tokens": [51250, 466, 309, 456, 311, 257, 2960, 510, 309, 311, 1219, 3414, 1590, 293, 286, 2041, 300, 390, 1027, 51590], "temperature": 0.0, "avg_logprob": -0.26365417730612833, "compression_ratio": 1.6266666666666667, "no_speech_prob": 0.05744779855012894}, {"id": 18, "seek": 12376, "start": 123.76, "end": 129.12, "text": " especially for idiots making YouTube videos and they had lots of foresight", "tokens": [50364, 2318, 337, 36454, 1455, 3088, 2145, 293, 436, 632, 3195, 295, 2091, 28654, 50632], "temperature": 0.0, "avg_logprob": -0.2312318281693892, "compression_ratio": 1.471698113207547, "no_speech_prob": 0.02402791567146778}, {"id": 19, "seek": 12376, "start": 129.12, "end": 136.12, "text": " so this is what it does it just gets set in an infinite infinite loop but let's", "tokens": [50632, 370, 341, 307, 437, 309, 775, 309, 445, 2170, 992, 294, 364, 13785, 13785, 6367, 457, 718, 311, 50982], "temperature": 0.0, "avg_logprob": -0.2312318281693892, "compression_ratio": 1.471698113207547, "no_speech_prob": 0.02402791567146778}, {"id": 20, "seek": 12376, "start": 136.12, "end": 144.64000000000001, "text": " understand why that is so let's clear everything and I'll do a regular division", "tokens": [50982, 1223, 983, 300, 307, 370, 718, 311, 1850, 1203, 293, 286, 603, 360, 257, 3890, 10044, 51408], "temperature": 0.0, "avg_logprob": -0.2312318281693892, "compression_ratio": 1.471698113207547, "no_speech_prob": 0.02402791567146778}, {"id": 21, "seek": 14464, "start": 144.64, "end": 159.11999999999998, "text": " though of my favorite one which gives pi 355 dividend divided by 113 and again", "tokens": [50364, 1673, 295, 452, 2954, 472, 597, 2709, 3895, 6976, 20, 29796, 6666, 538, 2975, 18, 293, 797, 51088], "temperature": 0.0, "avg_logprob": -0.28095245361328125, "compression_ratio": 1.4805194805194806, "no_speech_prob": 0.07152391970157623}, {"id": 22, "seek": 14464, "start": 159.11999999999998, "end": 165.6, "text": " I'll try to do it from the edge here so what happens is that in order to do", "tokens": [51088, 286, 603, 853, 281, 360, 309, 490, 264, 4691, 510, 370, 437, 2314, 307, 300, 294, 1668, 281, 360, 51412], "temperature": 0.0, "avg_logprob": -0.28095245361328125, "compression_ratio": 1.4805194805194806, "no_speech_prob": 0.07152391970157623}, {"id": 23, "seek": 14464, "start": 165.6, "end": 171.92, "text": " divisions what it actually does is successive subtractions and does it as", "tokens": [51412, 24328, 437, 309, 767, 775, 307, 48043, 16390, 626, 293, 775, 309, 382, 51728], "temperature": 0.0, "avg_logprob": -0.28095245361328125, "compression_ratio": 1.4805194805194806, "no_speech_prob": 0.07152391970157623}, {"id": 24, "seek": 17192, "start": 171.92, "end": 176.6, "text": " we do it in school is trial and error so it will try to subtract what I just", "tokens": [50364, 321, 360, 309, 294, 1395, 307, 7308, 293, 6713, 370, 309, 486, 853, 281, 16390, 437, 286, 445, 50598], "temperature": 0.0, "avg_logprob": -0.20486706495285034, "compression_ratio": 1.628691983122363, "no_speech_prob": 0.02795216254889965}, {"id": 25, "seek": 17192, "start": 176.6, "end": 183.79999999999998, "text": " entered which is 113 from this number and trying progressively know this time", "tokens": [50598, 9065, 597, 307, 2975, 18, 490, 341, 1230, 293, 1382, 46667, 458, 341, 565, 50958], "temperature": 0.0, "avg_logprob": -0.20486706495285034, "compression_ratio": 1.628691983122363, "no_speech_prob": 0.02795216254889965}, {"id": 26, "seek": 17192, "start": 183.79999999999998, "end": 189.23999999999998, "text": " 10, 900, 1000 until it hits over here and finally it subtracts enough of a", "tokens": [50958, 1266, 11, 22016, 11, 9714, 1826, 309, 8664, 670, 510, 293, 2721, 309, 16390, 82, 1547, 295, 257, 51230], "temperature": 0.0, "avg_logprob": -0.20486706495285034, "compression_ratio": 1.628691983122363, "no_speech_prob": 0.02795216254889965}, {"id": 27, "seek": 17192, "start": 189.23999999999998, "end": 194.48, "text": " chunk that it overflows and it tells it it has subtracted too much and then it", "tokens": [51230, 16635, 300, 309, 670, 33229, 293, 309, 5112, 309, 309, 575, 16390, 292, 886, 709, 293, 550, 309, 51492], "temperature": 0.0, "avg_logprob": -0.20486706495285034, "compression_ratio": 1.628691983122363, "no_speech_prob": 0.02795216254889965}, {"id": 28, "seek": 17192, "start": 194.48, "end": 200.16, "text": " starts to move it one to the left and subtract smaller amounts and that's how", "tokens": [51492, 3719, 281, 1286, 309, 472, 281, 264, 1411, 293, 16390, 4356, 11663, 293, 300, 311, 577, 51776], "temperature": 0.0, "avg_logprob": -0.20486706495285034, "compression_ratio": 1.628691983122363, "no_speech_prob": 0.02795216254889965}, {"id": 29, "seek": 20016, "start": 200.16, "end": 206.28, "text": " it does the division eventually so let's see how that works", "tokens": [50364, 309, 775, 264, 10044, 4728, 370, 718, 311, 536, 577, 300, 1985, 50670], "temperature": 0.0, "avg_logprob": -0.5159337703998272, "compression_ratio": 1.5655737704918034, "no_speech_prob": 0.0028271812479943037}, {"id": 30, "seek": 20016, "start": 206.28, "end": 213.0, "text": " see it move move move move move move move ding it overflows", "tokens": [50670, 536, 309, 1286, 1286, 1286, 1286, 1286, 1286, 1286, 21211, 309, 670, 33229, 51006], "temperature": 0.0, "avg_logprob": -0.5159337703998272, "compression_ratio": 1.5655737704918034, "no_speech_prob": 0.0028271812479943037}, {"id": 31, "seek": 20016, "start": 216.48, "end": 224.24, "text": " and eventually it divide in and it's in the 3.141592 something it's the", "tokens": [51180, 293, 4728, 309, 9845, 294, 293, 309, 311, 294, 264, 805, 13, 7271, 5211, 21821, 746, 309, 311, 264, 51568], "temperature": 0.0, "avg_logprob": -0.5159337703998272, "compression_ratio": 1.5655737704918034, "no_speech_prob": 0.0028271812479943037}, {"id": 32, "seek": 22424, "start": 224.24, "end": 227.28, "text": " approximation of pi", "tokens": [50366, 28023, 295, 3895, 50516], "temperature": 0.0, "avg_logprob": -0.5529392957687378, "compression_ratio": 0.7037037037037037, "no_speech_prob": 0.33452051877975464}, {"id": 33, "seek": 25424, "start": 254.24, "end": 280.24, "text": " so what happens that when you divide by zero is just subtract nothing and so it", "tokens": [50364, 370, 437, 2314, 300, 562, 291, 9845, 538, 4018, 307, 445, 16390, 1825, 293, 370, 309, 51664], "temperature": 0.0, "avg_logprob": -0.35323338508605956, "compression_ratio": 1.1126760563380282, "no_speech_prob": 0.008525504730641842}, {"id": 34, "seek": 28024, "start": 280.24, "end": 286.28000000000003, "text": " can never overflow and it gets stuck in an infinite loop so here you go here you", "tokens": [50364, 393, 1128, 37772, 293, 309, 2170, 5541, 294, 364, 13785, 6367, 370, 510, 291, 352, 510, 291, 50666], "temperature": 0.0, "avg_logprob": -0.3587821960449219, "compression_ratio": 1.3284671532846715, "no_speech_prob": 0.19617590308189392}, {"id": 35, "seek": 28024, "start": 286.28000000000003, "end": 293.64, "text": " have it divide by zero on a Frieden STW10 let's do it again", "tokens": [50666, 362, 309, 9845, 538, 4018, 322, 257, 17605, 268, 4904, 54, 3279, 718, 311, 360, 309, 797, 51034], "temperature": 0.0, "avg_logprob": -0.3587821960449219, "compression_ratio": 1.3284671532846715, "no_speech_prob": 0.19617590308189392}, {"id": 36, "seek": 28024, "start": 293.64, "end": 300.12, "text": " as clear enter some kind of stupid number", "tokens": [51034, 382, 1850, 3242, 512, 733, 295, 6631, 1230, 51358], "temperature": 0.0, "avg_logprob": -0.3587821960449219, "compression_ratio": 1.3284671532846715, "no_speech_prob": 0.19617590308189392}, {"id": 37, "seek": 30012, "start": 300.12, "end": 309.2, "text": " dividend all to the right here the keyboard divide by zero and watch the", "tokens": [50364, 29796, 439, 281, 264, 558, 510, 264, 10186, 9845, 538, 4018, 293, 1159, 264, 50818], "temperature": 0.0, "avg_logprob": -0.5851643880208334, "compression_ratio": 1.2747252747252746, "no_speech_prob": 0.07042303681373596}, {"id": 38, "seek": 30012, "start": 309.2, "end": 311.48, "text": " smoke", "tokens": [50818, 8439, 50932], "temperature": 0.0, "avg_logprob": -0.5851643880208334, "compression_ratio": 1.2747252747252746, "no_speech_prob": 0.07042303681373596}, {"id": 39, "seek": 30012, "start": 317.68, "end": 323.16, "text": " okay we'll do that forever good night", "tokens": [51242, 1392, 321, 603, 360, 300, 5680, 665, 1818, 51516], "temperature": 0.0, "avg_logprob": -0.5851643880208334, "compression_ratio": 1.2747252747252746, "no_speech_prob": 0.07042303681373596}, {"id": 40, "seek": 33012, "start": 330.12, "end": 346.74, "text": " a brilliant cast Jack Lemon in a delightful role which gives full reign to", "tokens": [50364, 257, 10248, 4193, 4718, 35404, 294, 257, 35194, 3090, 597, 2709, 1577, 20350, 281, 51195], "temperature": 0.0, "avg_logprob": -0.4940871000289917, "compression_ratio": 1.1477272727272727, "no_speech_prob": 0.02478375844657421}, {"id": 41, "seek": 33012, "start": 346.74, "end": 350.24, "text": " Jack's amazing versatility", "tokens": [51195, 4718, 311, 2243, 1774, 20758, 51370], "temperature": 0.0, "avg_logprob": -0.4940871000289917, "compression_ratio": 1.1477272727272727, "no_speech_prob": 0.02478375844657421}, {"id": 42, "seek": 36012, "start": 360.12, "end": 362.18, "text": " you", "tokens": [50364, 291, 50467], "temperature": 0.0, "avg_logprob": -0.8917098641395569, "compression_ratio": 0.2727272727272727, "no_speech_prob": 0.6159233450889587}], "language": "en"}